DockPhos.py
DockPhos-4.6.dist-info/LICENSE.md
DockPhos-4.6.dist-info/METADATA
DockPhos-4.6.dist-info/WHEEL
DockPhos-4.6.dist-info/entry_points.txt
DockPhos-4.6.dist-info/top_level.txt
DockPhos-4.6.dist-info/RECORD
