Metadata-Version: 2.1
Name: DockPhos
Version: 4.6
Summary: Helper script for using the Phosphoros Docker container
Home-page: https://gitlab.euclid-sgs.uk//SDC-CH/SDCCH_DockerPhosphoros
Author: SDC-CH
Author-email: sdc-ch@unige.ch
License: UNKNOWN
Platform: UNKNOWN
Classifier: Programming Language :: Python :: 3
Classifier: License :: OSI Approved :: GNU Lesser General Public License v3 or later (LGPLv3+)
Classifier: Operating System :: OS Independent
Classifier: Development Status :: 4 - Beta
Requires-Python: >=3.1
Requires-Dist: coloredlogs
Requires-Dist: requests
Requires-Dist: packaging
